Metadata-Version: 2.1
Name: omiga
Version: 2023.8.21
Summary: A package used to make 2D games
Home-page: 
Author: 嘎~
Author-email: chenjinhao2008@hotmail.com
Maintainer: 嘎~
Maintainer-email: chenejinhao2008@hotmail.com
License: MIT License
Classifier: Development Status :: 3 - Alpha
Classifier: Intended Audience :: Developers
Classifier: Topic :: Software Development :: Build Tools
Classifier: License :: OSI Approved :: MIT License
Classifier: Programming Language :: Python :: 3
Requires-Python: >=3.9
